{
  "type": "FeatureCollection",
  "features": [
    {
      "type": "Feature",
      "geometry": {
        "type": "Point",
        "coordinates": [26.663551920662563, 81.10855634726947]
      },
      "properties": {
        "क्र": 1,
        "नाम": "दतं िावन कु ण्ड",
        "परि": "पचंकोसी",
        "गाा": "बिहटा",
        "तहस": "अयोध्या",
        "जनप": "अयोध्या",
        "प्र": "कु ण्ड",
        "क्ष": "0.183",
        "गाट": "44"
      }
    },
    {
      "type": "Feature",
      "geometry": {
        "type": "Point",
        "coordinates": [26.661052876226194, 81.10850007325733]
      },
      "properties": {
        "क्र": 2,
        "नाम": "क्षीि सागि",
        "परि": "पचंकोसी",
        "गाा": "बिहटा",
        "तहस": "अयोध्या",
        "जनप": "अयोध्या",
        "प्र": "कु ण्ड",
        "क्ष": "*",
        "गाट": "*"
      }
    },
    {
      "type": "Feature",
      "geometry": {
        "type": "Point",
        "coordinates": [26.658167384218817, 81.10846239944587]
      },
      "properties": {
        "क्र": 3,
        "नाम": "रुक्मधि कु ण्ड",
        "परि": "पचंकोसी",
        "गाा": "जलवानपिु",
        "तहस": "अयोध्या",
        "जनप": "अयोध्या",
        "प्र": "कु ण्ड",
        "क्ष": "*",
        "गाट": "*"
      }
    },
    {
      "type": "Feature",
      "geometry": {
        "type": "Point",
        "coordinates": [26.660589064369354, 81.10834712517396]
      },
      "properties": {
        "क्र": 4,
        "नाम": "वधिष्ठ कु ण्ड",
        "परि": "पचंकोसी",
        "गाा": "अविखास",
        "तहस": "अयोध्या",
        "जनप": "अयोध्या",
        "प्र": "कु ण्ड",
        "क्ष": "नजलू",
        "गाट": "नजलू"
      }
    },
    {
      "type": "Feature",
      "geometry": {
        "type": "Point",
        "coordinates": [26.66355925073592, 81.10837498220515]
      },
      "properties": {
        "क्र": 5,
        "नाम": "सागि कु ण्ड",
        "परि": "पचंकोसी",
        "गाा": "कोट िामचन्दि",
        "तहस": "अयोध्या",
        "जनप": "अयोध्या",
        "प्र": "कु ण्ड",
        "क्ष": "जन्मभधम परिसिू",
        "गाट": "जन्मभधम परिसिू"
      }
    },
    {
      "type": "Feature",
      "geometry": {
        "type": "Point",
        "coordinates": [26.66991332241261, 81.10847867100985]
      },
      "properties": {
        "क्र": 6,
        "नाम": "धवभीषि कु ण्ड",
        "परि": "पचंकोसी",
        "गाा": "अविखास",
        "तहस": "अयोध्या",
        "जनप": "अयोध्या",
        "प्र": "कु ण्ड",
        "क्ष": "नजलू",
        "गाट": "नजलू"
      }
    },
    {
      "type": "Feature",
      "geometry": {
        "type": "Point",
        "coordinates": [26.6702048804083, 81.10855248090121]
      },
      "properties": {
        "क्र": 7,
        "नाम": "सप्तसागि",
        "परि": "पचंकोसी",
        "गाा": "मीिापि डु िावीबीे",
        "तहस": "अयोध्या",
        "जनप": "अयोध्या",
        "प्र": "कु ण्ड",
        "क्ष": "2",
        "गाट": "69"
      }
    },
    {
      "type": "Feature",
      "geometry": {
        "type": "Point",
        "coordinates": [26.663066065202873, 81.10859350643132]
      },
      "properties": {
        "क्र": 8,
        "नाम": "सग्रीव कु ु ण्ड",
        "परि": "पचंकोसी",
        "गाा": "बिहटा",
        "तहस": "अयोध्या",
        "जनप": "अयोध्या",
        "प्र": "कु ण्ड",
        "क्ष": "*",
        "गाट": "*"
      }
    },
    {
      "type": "Feature",
      "geometry": {
        "type": "Point",
        "coordinates": [26.661445231111657, 81.10859542627037]
      },
      "properties": {
        "क्र": 9,
        "नाम": "हनमान कु ु ण्ड",
        "परि": "पचंकोसी",
        "गाा": "बिहटा",
        "तहस": "अयोध्या",
        "जनप": "अयोध्या",
        "प्र": "कु ण्ड",
        "क्ष": "0.073",
        "गाट": "332"
      }
    },
    {
      "type": "Feature",
      "geometry": {
        "type": "Point",
        "coordinates": [26.659232410897154, 81.10861709136088]
      },
      "properties": {
        "क्र": 10,
        "नाम": "स्विणखधन कु ण्ड",
        "परि": "पचंकोसी",
        "गाा": "बिहटा",
        "तहस": "अयोध्या",
        "जनप": "अयोध्या",
        "प्र": "कु ण्ड",
        "क्ष": "0.139",
        "गाट": "353"
      }
    },
    {
      "type": "Feature",
      "geometry": {
        "type": "Point",
        "coordinates": [26.651500286296244, 81.10859406621022]
      },
      "properties": {
        "क्र": 11,
        "नाम": "सीता कु ण्ड",
        "परि": "पचंकोसी",
        "गाा": "बासपू ि धसिसाु",
        "तहस": "अयोध्या",
        "जनप": "अयोध्या",
        "प्र": "कु ण्ड",
        "क्ष": "0.626",
        "गाट": "295"
      }
    },
    {
      "type": "Feature",
      "geometry": {
        "type": "Point",
        "coordinates": [26.65297653477117, 81.10855241979027]
      },
      "properties": {
        "क्र": 12,
        "नाम": "अधनन कु ण्ड",
        "परि": "पचंकोसी",
        "गाा": "बासपू ि धसिसाु",
        "तहस": "अयोध्या",
        "जनप": "अयोध्या",
        "प्र": "कु ण्ड",
        "क्ष": "0.123",
        "गाट": "231"
      }
    },
    {
      "type": "Feature",
      "geometry": {
        "type": "Point",
        "coordinates": [26.65206591371415, 81.10852983978194]
      },
      "properties": {
        "क्र": 13,
        "नाम": "धवद्या कु ण्ड",
        "परि": "पचंकोसी",
        "गाा": "बासपू ि धसिसाु",
        "तहस": "अयोध्या",
        "जनप": "अयोध्या",
        "प्र": "कु ण्ड",
        "क्ष": "0.594",
        "गाट": "23"
      }
    },
    {
      "type": "Feature",
      "geometry": {
        "type": "Point",
        "coordinates": [26.647002660565555, 81.10855844283567]
      },
      "properties": {
        "क्र": 14,
        "नाम": "खजण कू ु ण्ड",
        "परि": "पचंकोसी",
        "गाा": "बासपू ि धसिसाु",
        "तहस": "अयोध्या",
        "जनप": "अयोध्या",
        "प्र": "कु ण्ड",
        "क्ष": "0.266",
        "गाट": "35"
      }
    },
    {
      "type": "Feature",
      "geometry": {
        "type": "Point",
        "coordinates": [26.650699781671484, 81.10847788988985]
      },
      "properties": {
        "क्र": 15,
        "नाम": "गिि के ु ण्ड",
        "परि": "पचंकोसी",
        "गाा": "काजीपि धचतावांु",
        "तहस": "अयोध्या",
        "जनप": "अयोध्या",
        "प्र": "कु ण्ड",
        "क्ष": "0.152",
        "गाट": "78"
      }
    },
    {
      "type": "Feature",
      "geometry": {
        "type": "Point",
        "coordinates": [26.64416794548131, 81.10847016573577]
      },
      "properties": {
        "क्र": 16,
        "नाम": "दििथ कु ण्ड",
        "परि": "पचंकोसी",
        "गाा": "हवतपै िु",
        "तहस": "अयोध्या",
        "जनप": "अयोध्या",
        "प्र": "कु ण्ड",
        "क्ष": "0.822",
        "गाट": "135"
      }
    },
    {
      "type": "Feature",
      "geometry": {
        "type": "Point",
        "coordinates": [26.650685859331862, 81.10838847022633]
      },
      "properties": {
        "क्र": 17,
        "नाम": "कौिल्या कु ण्ड",
        "परि": "पचंकोसी",
        "गाा": "वाग धवजयसी",
        "तहस": "अयोध्या",
        "जनप": "अयोध्या",
        "प्र": "कु ण्ड",
        "क्ष": "0.063",
        "गाट": "321"
      }
    },
    {
      "type": "Feature",
      "geometry": {
        "type": "Point",
        "coordinates": [26.650502230896073, 81.10837143084234]
      },
      "properties": {
        "क्र": 18,
        "नाम": "सधमत्रा कु ु ण्ड",
        "परि": "पचंकोसी",
        "गाा": "वाग धवजयसी",
        "तहस": "अयोध्या",
        "जनप": "अयोध्या",
        "प्र": "कु ण्ड",
        "क्ष": "0.089",
        "गाट": "331"
      }
    },
    {
      "type": "Feature",
      "geometry": {
        "type": "Point",
        "coordinates": [26.647206603247856, 81.10833160307928]
      },
      "properties": {
        "क्र": 19,
        "नाम": "कै के यी  कु ण्ड(भित)",
        "परि": "पचंकोसी",
        "गाा": "धजयनपिु",
        "तहस": "अयोध्या",
        "जनप": "अयोध्या",
        "प्र": "कु ण्ड",
        "क्ष": "0.196",
        "गाट": "32"
      }
    },
    {
      "type": "Feature",
      "geometry": {
        "type": "Point",
        "coordinates": [26.646448818828627, 81.1082916155579]
      },
      "properties": {
        "क्र": 20,
        "नाम": "दिभिसि कु ु ण्ड",
        "परि": "पचंकोसी",
        "गाा": "िानोपाली",
        "तहस": "अयोध्या",
        "जनप": "अयोध्या",
        "प्र": "कु ण्ड",
        "क्ष": "0.044",
        "गाट": "104"
      }
    },
    {
      "type": "Feature",
      "geometry": {
        "type": "Point",
        "coordinates": [26.643783235404204, 81.10825944299039]
      },
      "properties": {
        "क्र": 21,
        "नाम": "महाभिसि कु ण्ड",
        "परि": "चौदहकोसी",
        "गाा": "िानोपाली",
        "तहस": "अयोध्या",
        "जनप": "अयोध्या",
        "प्र": "कु ण्ड",
        "क्ष": ".7670, .1010, .7170,",
        "गाट": "245, 246"
      }
    },
    {
      "type": "Feature",
      "geometry": {
        "type": "Point",
        "coordinates": [26.6574892276548, 81.10835076135315]
      },
      "properties": {
        "क्र": 22,
        "नाम": "बहस्पधत कृ ु ण्ड",
        "परि": "पचंकोसी",
        "गाा": "वाग धवजयसी",
        "तहस": "अयोध्या",
        "जनप": "अयोध्या",
        "प्र": "कु ण्ड",
        "क्ष": "*",
        "गाट": "*"
      }
    },
    {
      "type": "Feature",
      "geometry": {
        "type": "Point",
        "coordinates": [26.65882952284154, 81.10833195327496]
      },
      "properties": {
        "क्र": 23,
        "नाम": "िनयक्ष कु ण्ड",
        "परि": "पचंकोसी",
        "गाा": "अविखास",
        "तहस": "अयोध्या",
        "जनप": "अयोध्या",
        "प्र": "कु ण्ड",
        "क्ष": "नजलू",
        "गाट": "नजलू"
      }
    },
    {
      "type": "Feature",
      "geometry": {
        "type": "Point",
        "coordinates": [26.6550781695873, 81.10828104205606]
      },
      "properties": {
        "क्र": 24,
        "नाम": "उवणिीकु ण्ड",
        "परि": "पचंकोसी",
        "गाा": "िानोपाली",
        "तहस": "अयोध्या",
        "जनप": "अयोध्या",
        "प्र": "कु ण्ड",
        "क्ष": "*",
        "गाट": "*"
      }
    },
    {
      "type": "Feature",
      "geometry": {
        "type": "Point",
        "coordinates": [26.666053672827566, 81.10833043339304]
      },
      "properties": {
        "क्र": 25,
        "नाम": "बह्मकु ण्ड",
        "परि": "पचंकोसी",
        "गाा": "अविखास",
        "तहस": "अयोध्या",
        "जनप": "अयोध्या",
        "प्र": "कु ण्ड",
        "क्ष": "नजलू",
        "गाट": "नजलू"
      }
    },
    {
      "type": "Feature",
      "geometry": {
        "type": "Point",
        "coordinates": [26.625930849517353, 81.10870191941393]
      },
      "properties": {
        "क्र": 26,
        "नाम": "वतििी कै ु ण्ड",
        "परि": "चौदहकोसी",
        "गाा": "कु ढ़ा के िवपि ु",
        "तहस": "अयोध्या",
        "जनप": "अयोध्या",
        "प्र": "कु ण्ड",
        "क्ष": "2.126",
        "गाट": "475"
      }
    },
    {
      "type": "Feature",
      "geometry": {
        "type": "Point",
        "coordinates": [26.62079531571461, 81.1086413603935]
      },
      "properties": {
        "क्र": 27,
        "नाम": "सयू ण कु ण्ड",
        "परि": "चौदहकोसी",
        "गाा": "कु ढ़ा के िवपि ु",
        "तहस": "अयोध्या",
        "जनप": "अयोध्या",
        "प्र": "कु ण्ड",
        "क्ष": "4.486",
        "गाट": "764"
      }
    },
    null,
    null,
    {
      "type": "Feature",
      "geometry": {
        "type": "Point",
        "coordinates": [26.623846765098126, 81.1085322449787]
      },
      "properties": {
        "क्र": 30,
        "नाम": "िधत कु ण्ड",
        "परि": "चौदहकोसी",
        "गाा": "कु िमाहा",
        "तहस": "अयोध्या",
        "जनप": "अयोध्या",
        "प्र": "कु ण्ड",
        "क्ष": "*",
        "गाट": "*"
      }
    },
    {
      "type": "Feature",
      "geometry": {
        "type": "Point",
        "coordinates": [26.622892003384422, 81.1084384944899]
      },
      "properties": {
        "क्र": 31,
        "नाम": "कु समायु िकु ु ण्ड",
        "परि": "चौदहकोसी",
        "गाा": "कु िमाहा",
        "तहस": "अयोध्या",
        "जनप": "अयोध्या",
        "प्र": "कु ण्ड",
        "क्ष": "0.481",
        "गाट": "339"
      }
    },
    {
      "type": "Feature",
      "geometry": {
        "type": "Point",
        "coordinates": [26.621406638406615, 81.10845222628718]
      },
      "properties": {
        "क्र": 32,
        "नाम": "दगाु ण कु ण्ड",
        "परि": "चौदहकोसी",
        "गाा": "कु िमाहा",
        "तहस": "अयोध्या",
        "जनप": "अयोध्या",
        "प्र": "कु ण्ड",
        "क्ष": "0.532",
        "गाट": "473"
      }
    },
    {
      "type": "Feature",
      "geometry": {
        "type": "Point",
        "coordinates": [26.633538120614798, 81.10761713806893]
      },
      "properties": {
        "क्र": 33,
        "नाम": "धगिजा कु ण्ड",
        "परि": "चौदहकोसी",
        "गाा": "जौनौिा",
        "तहस": "अयोध्या",
        "जनप": "अयोध्या",
        "प्र": "कु ण्ड",
        "क्ष": "0.556",
        "गाट": "589"
      }
    },
    {
      "type": "Feature",
      "geometry": {
        "type": "Point",
        "coordinates": [26.641168259683745, 81.10758311099885]
      },
      "properties": {
        "क्र": 34,
        "नाम": "श्रीसिोवि",
        "परि": "चौदहकोसी",
        "गाा": "लालबाग",
        "तहस": "अयोध्या",
        "जनप": "अयोध्या",
        "प्र": "कु ण्ड(मंधदि)",
        "क्ष": "0.279",
        "गाट": "4713"
      }
    },
    {
      "type": "Feature",
      "geometry": {
        "type": "Point",
        "coordinates": [26.64148937717798, 81.10789894715437]
      },
      "properties": {
        "क्र": 35,
        "नाम": "िीतलादवी े",
        "परि": "चौदहकोसी",
        "गाा": "दवकाली े",
        "तहस": "अयोध्या",
        "जनप": "अयोध्या",
        "प्र": "कु ण्ड(मंधदि)",
        "क्ष": "0.297",
        "गाट": "407"
      }
    },
    {
      "type": "Feature",
      "geometry": {
        "type": "Point",
        "coordinates": [26.663548937508516, 81.10705866034944]
      },
      "properties": {
        "क्र": 36,
        "नाम": "धनमणली कु ण्ड",
        "परि": "चौदहकोसी",
        "गाा": "कैं ट क्षत्रे",
        "तहस": "अयोध्या",
        "जनप": "अयोध्या",
        "प्र": "कु ण्ड(मंधदि)",
        "क्ष": "*",
        "गाट": "*"
      }
    },
    {
      "type": "Feature",
      "geometry": {
        "type": "Point",
        "coordinates": [26.65212158740572, 81.1080224600828]
      },
      "properties": {
        "क्र": 37,
        "नाम": "योधगनीकु ण्ड",
        "परि": "पचंकोसी",
        "गाा": "फै जाबाद",
        "तहस": "अयोध्या",
        "जनप": "अयोध्या",
        "प्र": "कु ण्ड",
        "क्ष": "*",
        "गाट": "*"
      }
    },
    {
      "type": "Feature",
      "geometry": {
        "type": "Point",
        "coordinates": [26.651233042205057, 81.10809557798291]
      },
      "properties": {
        "क्र": 38,
        "नाम": "िक्रकु ण्ड",
        "परि": "पचंकोसी",
        "गाा": "माझा जमथिा",
        "तहस": "अयोध्या",
        "जनप": "अयोध्या",
        "प्र": "कु ण्ड",
        "क्ष": "नजलू",
        "गाट": "261"
      }
    },
    {
      "type": "Feature",
      "geometry": {
        "type": "Point",
        "coordinates": [26.611412359593572, 81.10896956979911]
      },
      "properties": {
        "क्र": 39,
        "नाम": "धत्रपिािी जी ू",
        "परि": "चौिासीकोस",
        "गाा": "धतहुिा",
        "तहस": "अयोध्या",
        "जनप": "अयोध्या",
        "प्र": "कु ण्ड",
        "क्ष": "*",
        "गाट": "*"
      }
    },
    {
      "type": "Feature",
      "geometry": {
        "type": "Point",
        "coordinates": [26.521038684015256, 81.10942206230082]
      },
      "properties": {
        "क्र": 40,
        "नाम": "पण्यहरि ु",
        "परि": "चौिासीकोस",
        "गाा": "खानपिु",
        "तहस": "अयोध्या",
        "जनप": "अयोध्या",
        "प्र": "कु ण्ड",
        "क्ष": "2.478",
        "गाट": "831"
      }
    },
    {
      "type": "Feature",
      "geometry": {
        "type": "Point",
        "coordinates": [26.446511383422546, 81.10770967366898]
      },
      "properties": {
        "क्र": 41,
        "नाम": "हनमान कु ु ण्ड",
        "परि": "चौिासीकोस",
        "गाा": "तािोमाफी",
        "तहस": "बीकापिु",
        "जनप": "अयोध्या",
        "प्र": "कु ण्ड",
        "क्ष": "*",
        "गाट": "*"
      }
    },
    {
      "type": "Feature",
      "geometry": {
        "type": "Point",
        "coordinates": [26.44691024435773, 81.10768724006718]
      },
      "properties": {
        "क्र": 42,
        "नाम": "धवभीषि कु ण्ड",
        "परि": "चौिासीकोस",
        "गाा": "तािोमाफी",
        "तहस": "बीकापिु",
        "जनप": "अयोध्या",
        "प्र": "कु ण्ड",
        "क्ष": "*",
        "गाट": "*"
      }
    },
    {
      "type": "Feature",
      "geometry": {
        "type": "Point",
        "coordinates": [26.451322001282893, 81.10762681996417]
      },
      "properties": {
        "क्र": 43,
        "नाम": "सग्रीव कु ु ण्ड",
        "परि": "चौिासीकोस",
        "गाा": "तािोमाफी",
        "तहस": "बीकापिु",
        "जनप": "अयोध्या",
        "प्र": "कु ण्ड",
        "क्ष": "0.155",
        "गाट": "1832"
      }
    },
    {
      "type": "Feature",
      "geometry": {
        "type": "Point",
        "coordinates": [26.45277351718018, 81.10760461027374]
      },
      "properties": {
        "क्र": 44,
        "नाम": "िामकु ण्ड",
        "परि": "चौिासीकोस",
        "गाा": "तािोमाफी",
        "तहस": "बीकापिु",
        "जनप": "अयोध्या",
        "प्र": "कु ण्ड",
        "क्ष": "0.648",
        "गाट": "2007"
      }
    },
    {
      "type": "Feature",
      "geometry": {
        "type": "Point",
        "coordinates": [26.451443364214654, 81.10756309882724]
      },
      "properties": {
        "क्र": 45,
        "नाम": "सीता कु ण्ड",
        "परि": "चौिासीकोस",
        "गाा": "तािोमाफी",
        "तहस": "बीकापिु",
        "जनप": "अयोध्या",
        "प्र": "कु ण्ड",
        "क्ष": "0.228 - 0.911",
        "गाट": "1632-1633"
      }
    },
    {
      "type": "Feature",
      "geometry": {
        "type": "Point",
        "coordinates": [26.450903597158717, 81.10754665860736]
      },
      "properties": {
        "क्र": 46,
        "नाम": "भिव कै ु ण्ड",
        "परि": "चौिासीकोस",
        "गाा": "तािोमाफी",
        "तहस": "बीकापिु",
        "जनप": "अयोध्या",
        "प्र": "कु ण्ड",
        "क्ष": "0.038",
        "गाट": "1649"
      }
    },
    {
      "type": "Feature",
      "geometry": {
        "type": "Point",
        "coordinates": [26.55638304349043, 81.10528703100006]
      },
      "properties": {
        "क्र": 47,
        "नाम": "श्रवि क्षत्रे",
        "परि": "चौिासीकोस",
        "गाा": "धखहािन",
        "तहस": "सोहावल",
        "जनप": "अयोध्या",
        "प्र": "कु ण्ड(मंधदि)",
        "क्ष": "*",
        "गाट": "*"
      }
    },
    {
      "type": "Feature",
      "geometry": {
        "type": "Point",
        "coordinates": [26.641066560928248, 81.10292924952779]
      },
      "properties": {
        "क्र": 48,
        "नाम": "पिािि आश्रम",
        "परि": "चौिासीकोस",
        "गाा": "दविाकोटे",
        "तहस": "सोहावल",
        "जनप": "अयोध्या",
        "प्र": "आश्रम(कु ण्ड)",
        "क्ष": "*",
        "गाट": "*"
      }
    },
    {
      "type": "Feature",
      "geometry": {
        "type": "Point",
        "coordinates": [26.58563451728579, 81.1032134563081]
      },
      "properties": {
        "क्र": 49,
        "नाम": "च्यवनाश्रम",
        "परि": "चौिासीकोस",
        "गाा": "कंु दखाु ण कला",
        "तहस": "सोहावल",
        "जनप": "अयोध्या",
        "प्र": "आश्रम(कु ण्ड)",
        "क्ष": "*",
        "गाट": "*"
      }
    },
    {
      "type": "Feature",
      "geometry": {
        "type": "Point",
        "coordinates": [26.638815727803674, 81.1005038002721]
      },
      "properties": {
        "क्र": 50,
        "नाम": "गौतमाश्रम",
        "परि": "चौिासीकोस",
        "गाा": "रुदौली नगि",
        "तहस": "रुदौली",
        "जनप": "अयोध्या",
        "प्र": "आश्रम(कु ण्ड)",
        "क्ष": "*",
        "गाट": "*"
      }
    },
    {
      "type": "Feature",
      "geometry": {
        "type": "Point",
        "coordinates": [26.518157815206624, 81.10739861041479]
      },
      "properties": {
        "क्र": 51,
        "नाम": "मानस तीथण",
        "परि": "चौिासीकोस",
        "गाा": "िैथवा ु",
        "तहस": "सोहावल",
        "जनप": "अयोध्या",
        "प्र": "कु ण्ड",
        "क्ष": "*",
        "गाट": "*"
      }
    },
    {
      "type": "Feature",
      "geometry": {
        "type": "Point",
        "coordinates": [26.519497526984832, 81.10735288797885]
      },
      "properties": {
        "क्र": 52,
        "नाम": "धपिाचमोचन",
        "परि": "चौिासीकोस",
        "गाा": "िैथवा ु",
        "तहस": "सोहावल",
        "जनप": "अयोध्या",
        "प्र": "कु ण्ड",
        "क्ष": "*",
        "गाट": "*"
      }
    },
    {
      "type": "Feature",
      "geometry": {
        "type": "Point",
        "coordinates": [26.518715531628533, 81.10727336752927]
      },
      "properties": {
        "क्र": 53,
        "नाम": "गया कु ण्ड",
        "परि": "चौिासीकोस",
        "गाा": "भितकु ण्ड",
        "तहस": "सोहावल",
        "जनप": "अयोध्या",
        "प्र": "कु ण्ड",
        "क्ष": "*",
        "गाट": "*"
      }
    },
    {
      "type": "Feature",
      "geometry": {
        "type": "Point",
        "coordinates": [26.521693956921162, 81.10726578273847]
      },
      "properties": {
        "क्र": 54,
        "नाम": "भितकु ण्ड",
        "परि": "चौिासीकोस",
        "गाा": "भितकु ण्ड",
        "तहस": "सोहावल",
        "जनप": "अयोध्या",
        "प्र": "कु ण्ड",
        "क्ष": "*",
        "गाट": "*"
      }
    },
    {
      "type": "Feature",
      "geometry": {
        "type": "Point",
        "coordinates": [26.52326983060192, 81.10716873889088]
      },
      "properties": {
        "क्र": 55,
        "नाम": "जटाकु ण्ड",
        "परि": "चौिासीकोस",
        "गाा": "मसु पे िु",
        "तहस": "सोहावल",
        "जनप": "अयोध्या",
        "प्र": "कु ण्ड",
        "क्ष": "*",
        "गाट": "*"
      }
    },
    {
      "type": "Feature",
      "geometry": {
        "type": "Point",
        "coordinates": [26.519341659702015, 81.10700616080257]
      },
      "properties": {
        "क्र": 56,
        "नाम": "ित्रघ्न कु ु ण्ड",
        "परि": "चौिासीकोस",
        "गाा": "दोस्तपिु",
        "तहस": "सोहावल",
        "जनप": "अयोध्या",
        "प्र": "कु ण्ड",
        "क्ष": "*",
        "गाट": "*"
      }
    },
    null,
    {
      "type": "Feature",
      "geometry": {
        "type": "Point",
        "coordinates": [26.49243450224321, 81.1046717301562]
      },
      "properties": {
        "क्र": 58,
        "नाम": "आधस्तकाश्रम",
        "परि": "चौिासीकोस",
        "गाा": "",
        "तहस": "धमल्कीपिु",
        "जनप": "अयोध्या",
        "प्र": "आश्रम(कु ण्ड)",
        "क्ष": "*",
        "गाट": "*"
      }
    },
    null,
    null,
    null,
    null,
    null,
    null,
    null,
    {
      "type": "Feature",
      "geometry": {
        "type": "Point",
        "coordinates": [26.635037109888113, 81.10729738822315]
      },
      "properties": {
        "क्र": 66,
        "नाम": "खोजनपि तालाब ु 4",
        "परि": "चौिासीकोस",
        "गाा": "खोजनपिु",
        "तहस": "अयोध्या",
        "जनप": "अयोध्या",
        "प्र": "तालाब",
        "क्ष": "0.129",
        "गाट": "364"
      }
    },
    {
      "type": "Feature",
      "geometry": {
        "type": "Point",
        "coordinates": [26.635866794425674, 81.10731177921173]
      },
      "properties": {
        "क्र": 67,
        "नाम": "खोजनपि तालाब ु 5",
        "परि": "चौिासीकोस",
        "गाा": "खोजनपिु",
        "तहस": "अयोध्या",
        "जनप": "अयोध्या",
        "प्र": "तालाब",
        "क्ष": "0.197",
        "गाट": "391"
      }
    },
    null,
    {
      "type": "Feature",
      "geometry": {
        "type": "Point",
        "coordinates": [26.647740731670314, 81.10754348300793]
      },
      "properties": {
        "क्र": 69,
        "नाम": "फतगजंे  तालाब",
        "परि": "चौदहकोसी",
        "गाा": "फै जाबाद",
        "तहस": "अयोध्या",
        "जनप": "अयोध्या",
        "प्र": "तालाब",
        "क्ष": "*",
        "गाट": "*"
      }
    },
    {
      "type": "Feature",
      "geometry": {
        "type": "Point",
        "coordinates": [26.6424675373586, 81.1073978206071]
      },
      "properties": {
        "क्र": 70,
        "नाम": "तालाब स्टिनिोड े",
        "परि": "चौदहकोसी",
        "गाा": "फै जाबाद",
        "तहस": "अयोध्या",
        "जनप": "अयोध्या",
        "प्र": "तालाब",
        "क्ष": "*",
        "गाट": "*"
      }
    },
    {
      "type": "Feature",
      "geometry": {
        "type": "Point",
        "coordinates": [26.64798818060266, 81.10733253185077]
      },
      "properties": {
        "क्र": 71,
        "नाम": "लाल धडनगी",
        "परि": "चौदहकोसी",
        "गाा": "फै जाबाद",
        "तहस": "अयोध्या",
        "जनप": "अयोध्या",
        "प्र": "तालाब",
        "क्ष": "*",
        "गाट": "*"
      }
    },
    null,
    null,
    null,
    {
      "type": "Feature",
      "geometry": {
        "type": "Point",
        "coordinates": [26.640946546618757, 81.10692533155675]
      },
      "properties": {
        "क्र": 75,
        "नाम": "अब्ब सिाय तालाबू",
        "परि": "चौिासीकोस",
        "गाा": "अब्ब सिायू",
        "तहस": "अयोध्या",
        "जनप": "अयोध्या",
        "प्र": "तालाब",
        "क्ष": "1.912",
        "गाट": "403"
      }
    },
    {
      "type": "Feature",
      "geometry": {
        "type": "Point",
        "coordinates": [26.6356617499032, 81.10678721005254]
      },
      "properties": {
        "क्र": 76,
        "नाम": "अब्ब सिाय तालाब ू 2",
        "परि": "चौिासीकोस",
        "गाा": "अब्ब सिायू",
        "तहस": "अयोध्या",
        "जनप": "अयोध्या",
        "प्र": "तालाब",
        "क्ष": "2.239",
        "गाट": "1099"
      }
    },
    null,
    {
      "type": "Feature",
      "geometry": {
        "type": "Point",
        "coordinates": [26.640052084165628, 81.10752624211474]
      },
      "properties": {
        "क्र": 78,
        "नाम": "मक़बिा फै ज़ाबाद",
        "परि": "चौदहकोसी",
        "गाा": "जनौिा",
        "तहस": "अयोध्या",
        "जनप": "अयोध्या",
        "प्र": "तालाब",
        "क्ष": "1.48",
        "गाट": "210"
      }
    },
    {
      "type": "Feature",
      "geometry": {
        "type": "Point",
        "coordinates": [26.61476856919749, 81.1084846521066]
      },
      "properties": {
        "क्र": 79,
        "नाम": "अचािी का सगिा",
        "परि": "चौदहकोसी",
        "गाा": "कु ढ़ा के िवपि ु",
        "तहस": "अयोध्या",
        "जनप": "अयोध्या",
        "प्र": "तालाब",
        "क्ष": "2.475",
        "गाट": "356"
      }
    },
    null,
    {
      "type": "Feature",
      "geometry": {
        "type": "Point",
        "coordinates": [26.650703060337413, 81.10830777499969]
      },
      "properties": {
        "क्र": 81,
        "नाम": "िानोपाली 1",
        "परि": "चौदहकोसी",
        "गाा": "िानोपाली",
        "तहस": "अयोध्या",
        "जनप": "अयोध्या",
        "प्र": "तालाब",
        "क्ष": "0.658",
        "गाट": "99"
      }
    },
    {
      "type": "Feature",
      "geometry": {
        "type": "Point",
        "coordinates": [26.648124018834505, 81.10825454877397]
      },
      "properties": {
        "क्र": 82,
        "नाम": "िानोपाली 2",
        "परि": "चौदहकोसी",
        "गाा": "िानोपाली",
        "तहस": "अयोध्या",
        "जनप": "अयोध्या",
        "प्र": "तालाब",
        "क्ष": "0.297",
        "गाट": "221"
      }
    },
    null,
    null,
    null,
    null,
    null,
    null,
    null,
    null,
    null,
    null,
    null,
    {
      "type": "Feature",
      "geometry": {
        "type": "Point",
        "coordinates": [26.627889249454924, 81.10778119328758]
      },
      "properties": {
        "क्र": 94,
        "नाम": "जनौिा 1",
        "परि": "चौदहकोसी",
        "गाा": "जनौिा",
        "तहस": "अयोध्या",
        "जनप": "अयोध्या",
        "प्र": "तालाब",
        "क्ष": "1.265",
        "गाट": "625धम"
      }
    },
    {
      "type": "Feature",
      "geometry": {
        "type": "Point",
        "coordinates": [26.634107245030332, 81.10761752108907]
      },
      "properties": {
        "क्र": 95,
        "नाम": "जनौिा 2",
        "परि": "चौदहकोसी",
        "गाा": "जनौिा",
        "तहस": "अयोध्या",
        "जनप": "अयोध्या",
        "प्र": "तालाब",
        "क्ष": "*",
        "गाट": "604"
      }
    },
    {
      "type": "Feature",
      "geometry": {
        "type": "Point",
        "coordinates": [26.639585115613517, 81.10764993439729]
      },
      "properties": {
        "क्र": 96,
        "नाम": "मवतीपे िाु",
        "परि": "चौदहकोसी",
        "गाा": "जनौिा",
        "तहस": "अयोध्या",
        "जनप": "अयोध्या",
        "प्र": "तालाब",
        "क्ष": "0.784",
        "गाट": "440"
      }
    },
    null,
    null,
    null,
    null,
    {
      "type": "Feature",
      "geometry": {
        "type": "Point",
        "coordinates": [26.6061987642195, 81.10823073860028]
      },
      "properties": {
        "क्र": 101,
        "नाम": "गजंा",
        "परि": "चौिासीकोस",
        "गाा": "गजंा",
        "तहस": "अयोध्या",
        "जनप": "अयोध्या",
        "प्र": "तालाब",
        "क्ष": "3.531",
        "गाट": "681"
      }
    },
    {
      "type": "Feature",
      "geometry": {
        "type": "Point",
        "coordinates": [26.6457946925977, 81.10788997829643]
      },
      "properties": {
        "क्र": 102,
        "नाम": "दवकाली गांव े 1",
        "परि": "चौदहकोसी",
        "गाा": "दवकालीे",
        "तहस": "अयोध्या",
        "जनप": "अयोध्या",
        "प्र": "तालाब",
        "क्ष": "0.43",
        "गाट": "424"
      }
    },
    {
      "type": "Feature",
      "geometry": {
        "type": "Point",
        "coordinates": [26.64381876871069, 81.10792596536015]
      },
      "properties": {
        "क्र": 103,
        "नाम": "दवकाली गांव े 2",
        "परि": "चौदहकोसी",
        "गाा": "दवकालीे",
        "तहस": "अयोध्या",
        "जनप": "अयोध्या",
        "प्र": "तालाब",
        "क्ष": "0.353",
        "गाट": "391"
      }
    },
    {
      "type": "Feature",
      "geometry": {
        "type": "Point",
        "coordinates": [26.65287678152727, 81.10847094151059]
      },
      "properties": {
        "क्र": 104,
        "नाम": "मनमु धनु",
        "परि": "पचंकोसी",
        "गाा": "काजीपि धचतावांु",
        "तहस": "अयोध्या",
        "जनप": "अयोध्या",
        "प्र": "तालाब",
        "क्ष": "*",
        "गाट": "*"
      }
    },
    {
      "type": "Feature",
      "geometry": {
        "type": "Point",
        "coordinates": [26.64760623850789, 81.10754249428261]
      },
      "properties": {
        "क्र": 105,
        "नाम": "फतगजंे  2",
        "परि": "चौदहकोसी",
        "गाा": "फै जाबाद",
        "तहस": "अयोध्या",
        "जनप": "अयोध्या",
        "प्र": "तालाब",
        "क्ष": "नजलू",
        "गाट": "नजलू"
      }
    },
    {
      "type": "Feature",
      "geometry": {
        "type": "Point",
        "coordinates": [26.650318226430546, 81.1075464452566]
      },
      "properties": {
        "क्र": 106,
        "नाम": "महाजनी टोला",
        "परि": "चौदहकोसी",
        "गाा": "फै जाबाद",
        "तहस": "अयोध्या",
        "जनप": "अयोध्या",
        "प्र": "तालाब",
        "क्ष": "नजलू",
        "गाट": "नजलू"
      }
    },
    {
      "type": "Feature",
      "geometry": {
        "type": "Point",
        "coordinates": [26.537236443741413, 81.10801516790187]
      },
      "properties": {
        "क्र": 107,
        "नाम": "नारायणपर झीलु",
        "परि": "चौिासीकोस",
        "गाा": "नािायिपिु",
        "तहस": "अयोध्या",
        "जनप": "अयोध्या",
        "प्र": "तालाब",
        "क्ष": "7.072",
        "गाट": "783क"
      }
    },
    null
  ]
}
